{"format": "keras", "nodes": [{"name": "input_81", "id": "input_81", "class_name": "InputLayer", "output_shape": [[null, 224, 224, 3]], "num_parameters": 0}, {"name": "conv2d_153", "id": "conv2d_153", "class_name": "Conv2D", "output_shape": [null, 222, 222, 6], "num_parameters": 168}, {"name": "batch_normalization_303", "id": "batch_normalization_303", "class_name": "BatchNormalization", "output_shape": [null, 222, 222, 6], "num_parameters": 24}, {"name": "max_pooling2d_153", "id": "max_pooling2d_153", "class_name": "MaxPooling2D", "output_shape": [null, 111, 111, 6], "num_parameters": 0}, {"name": "dropout_151", "id": "dropout_151", "class_name": "Dropout", "output_shape": [null, 111, 111, 6], "num_parameters": 0}, {"name": "conv2d_154", "id": "conv2d_154", "class_name": "Conv2D", "output_shape": [null, 109, 109, 16], "num_parameters": 880}, {"name": "batch_normalization_304", "id": "batch_normalization_304", "class_name": "BatchNormalization", "output_shape": [null, 109, 109, 16], "num_parameters": 64}, {"name": "max_pooling2d_154", "id": "max_pooling2d_154", "class_name": "MaxPooling2D", "output_shape": [null, 54, 54, 16], "num_parameters": 0}, {"name": "flatten_76", "id": "flatten_76", "class_name": "Flatten", "output_shape": [null, 46656], "num_parameters": 0}, {"name": "dense_225", "id": "dense_225", "class_name": "Dense", "output_shape": [null, 128], "num_parameters": 5972096}, {"name": "batch_normalization_305", "id": "batch_normalization_305", "class_name": "BatchNormalization", "output_shape": [null, 128], "num_parameters": 512}, {"name": "dropout_152", "id": "dropout_152", "class_name": "Dropout", "output_shape": [null, 128], "num_parameters": 0}, {"name": "dense_226", "id": "dense_226", "class_name": "Dense", "output_shape": [null, 32], "num_parameters": 4128}, {"name": "batch_normalization_306", "id": "batch_normalization_306", "class_name": "BatchNormalization", "output_shape": [null, 32], "num_parameters": 128}, {"name": "dense_227", "id": "dense_227", "class_name": "Dense", "output_shape": [null, 1], "num_parameters": 33}], "edges": [["input_81", "conv2d_153"], ["conv2d_153", "batch_normalization_303"], ["batch_normalization_303", "max_pooling2d_153"], ["max_pooling2d_153", "dropout_151"], ["dropout_151", "conv2d_154"], ["conv2d_154", "batch_normalization_304"], ["batch_normalization_304", "max_pooling2d_154"], ["max_pooling2d_154", "flatten_76"], ["flatten_76", "dense_225"], ["dense_225", "batch_normalization_305"], ["batch_normalization_305", "dropout_152"], ["dropout_152", "dense_226"], ["dense_226", "batch_normalization_306"], ["batch_normalization_306", "dense_227"]]}